pysolcache
